vnstock_mcp/__init__.py
vnstock_mcp/server.py
vnstock_mcp/libs/__init__.py
vnstock_mcp/libs/ta_core.py
vnstock_mcp/libs/ta_momentum_utils.py
vnstock_mcp/libs/ta_trend_utils.py
vnstock_mcp/libs/ta_utils.py
vnstock_mcp/libs/ta_volume_utils.py
vnstock_mcp/libs/utils.py
vnstock_mcp/libs/vnstock_utils.py
vnstock_mcp/tools/__init__.py
vnstock_mcp/tools/company_tools.py
vnstock_mcp/tools/finance_tools.py
vnstock_mcp/tools/fund_tools.py
vnstock_mcp/tools/listing_tools.py
vnstock_mcp/tools/misc_tools.py
vnstock_mcp/tools/quote_tools.py
vnstock_mcp/tools/trading_tools.py
vnstock_mcp_server-1.0.4.dist-info/licenses/LICENSE
vnstock_mcp_server-1.0.4.dist-info/METADATA
vnstock_mcp_server-1.0.4.dist-info/WHEEL
vnstock_mcp_server-1.0.4.dist-info/entry_points.txt
vnstock_mcp_server-1.0.4.dist-info/top_level.txt
vnstock_mcp_server-1.0.4.dist-info/RECORD
