Metadata-Version: 2.4
Name: vnstock-mcp-server
Version: 1.0.4
Summary: An MCP server exposing tools to access Vietnam stock market data built on top of vnstock and mcp
Author-email: Mao Bui <maonguyen199873@gmail.com>
License: MIT
Project-URL: Homepage, https://github.com/MaoBui2907/vnstock-mcp-server
Project-URL: Repository, https://github.com/MaoBui2907/vnstock-mcp-server
Project-URL: Issues, https://github.com/MaoBui2907/vnstock-mcp-server
Keywords: mcp,vnstock,vietnam,stock,market,finance
Classifier: Development Status :: 5 - Production/Stable
Classifier: Intended Audience :: Developers
Classifier: Intended Audience :: Financial and Insurance Industry
Classifier: License :: OSI Approved :: MIT License
Classifier: Programming Language :: Python :: 3
Classifier: Programming Language :: Python :: 3.12
Classifier: Programming Language :: Python :: 3.13
Classifier: Topic :: Office/Business :: Financial
Classifier: Topic :: Software Development :: Libraries :: Python Modules
Requires-Python: <3.14,>=3.12
License-File: LICENSE
Requires-Dist: mcp>=1.13.1
Requires-Dist: vnstock>=3.2.6
Requires-Dist: fastmcp>=2.13.3
Requires-Dist: python-toon>=0.1.3
Requires-Dist: pandas-ta>=0.4.71b0
Dynamic: license-file
